snakeres/__init__.py
snakeres/parsing.py
snakeres/rules.py
snakeres/snakeres.py
snakeres/utils.py
snakeres/workflow_profile.py
snakeres-0.1.dist-info/METADATA
snakeres-0.1.dist-info/WHEEL
snakeres-0.1.dist-info/entry_points.txt
snakeres-0.1.dist-info/licenses/LICENSE
snakeres-0.1.dist-info/RECORD
