Metadata-Version: 2.4
Name: snakeres
Version: 0.1
Summary: Extract the resource specifications from a snakemake workflow and create a workflow profile
Project-URL: homepage, https://github.com/W-L/snakeres
License-File: LICENSE
Requires-Python: >=3.12
Requires-Dist: pyyaml
Provides-Extra: dev
Requires-Dist: pytest; extra == 'dev'
Requires-Dist: pytest-cov; extra == 'dev'
